django_boot
