Metadata-Version: 2.1
Name: django-boot
Version: 1.6.4
Summary: Django application with bootstrap-based theme.
Home-page: https://github.com/roderiano/django-boot
Author: Gabriel Silveira
Author-email: gabrielsilveirapro@gmail.com
License: MIT
Requires-Python: >=3.8
License-File: LICENSE
